{"singlePage": ["about"], "startSite": "11/29/2025", "filingNum": "", "onePageListNum": 15, "commentLabelColor": "#006b75", "yearColorList": ["#bc4c00", "#0969da", "#1f883d", "#A333D0"], "i18n": "CN", "themeMode": "manual", "dayTheme": "light", "nightTheme": "dark", "urlMode": "pinyin", "script": "<script src='https://blog.meekdai.com/Gmeek/plugins/GmeekTOC.js'></script><script src='https://blog.meekdai.com/Gmeek/plugins/lightbox.js'></script>", "style": "", "head": "", "indexScript": "", "indexStyle": "", "bottomText": "", "showPostSource": 1, "iconList": {"music": "<svg xmlns=\"http://www.w3.org/2000/svg\" viewBox=\"0 0 16 16\" width=\"16\" height=\"16\"><path d=\"M9 3v7.5a1.5 1.5 0 1 1-1-1.415V5L4 6v2.5A1.5 1.5 0 1 1 3 7.5V2h6z\"/></svg>"}, "UTC": 8, "rssSplit": "sentence", "exlink": {"music": "https://chii.in/user/zfyx_ice"}, "needComment": 0, "allHead": "<script src='https://blog.meekdai.com/Gmeek/plugins/GmeekVercount.js'></script>", "title": "\u30e6\u30ad\u306e\u90e8\u5c4b", "subTitle": "\u4e00\u4e2a\u7b80\u964b\u7684\u907f\u98ce\u6e2f", "avatarUrl": "https://avatars.githubusercontent.com/u/237422127?v=4", "GMEEK_VERSION": "last", "postListJson": {"P1": {"htmlDir": "docs/post/zhong-yu-da-hao-le.html", "labels": ["\u65e5\u5e38"], "postTitle": "\u7ec8\u4e8e\u642d\u597d\u4e86", "postUrl": "post/zhong-yu-da-hao-le.html", "postSourceUrl": "https://github.com/zfyx-ice/zfyx-ice.github.io/issues/1", "commentNum": 0, "wordCount": 98, "description": "\u5176\u5b9e\u6211\u5f88\u4e45\u4e4b\u524d\u5c31\u60f3\u642d\u4e00\u4e2a\u81ea\u5df1\u7684\u535a\u5ba2\u4e86\uff0c\u4f46\u7531\u4e8e\u81ea\u5df1\u7684\u52a8\u624b\u80fd\u529b\u6709\u9650\uff0c\u5c61\u6b21\u5c1d\u8bd5\u7ec8\u7a76\u672a\u80fd\u6210\u529f\uff0c\u8fd9\u6b21\u7ec8\u4e8e\u642d\u597d\u4e86\n\u6211\u4f1a\u5728\u8fd9\u91cc\u5199\u4e00\u4e9b\u81ea\u5df1\u7684\u6587\u7ae0\uff08\u5927\u6982\uff09\n### \u540e\u8bb0\n  tmd\u521a\u5f04\u597d\u7684\u88ab\u6211\u641e\u70b8\u4e86\uff0c\u91cd\u65b0\u6709\u5f04\u4e86\u4e00\u4e2a\u3002", "top": 0, "createdAt": 1764436332, "style": "", "script": "<script src='https://blog.meekdai.com/Gmeek/plugins/GmeekTOC.js'></script><script src='https://blog.meekdai.com/Gmeek/plugins/lightbox.js'></script>", "head": "", "ogImage": "https://avatars.githubusercontent.com/u/237422127?v=4", "createdDate": "2025-11-30", "dateLabelColor": "#0969da"}, "P2": {"htmlDir": "docs/post/xue-xi-yu-ri-chang.html", "labels": ["\u65e5\u5e38", "\u788e\u788e\u5ff5", "\u53d1\u7535"], "postTitle": "\u5b66\u4e60\u4e0e\u65e5\u5e38", "postUrl": "post/xue-xi-yu-ri-chang.html", "postSourceUrl": "https://github.com/zfyx-ice/zfyx-ice.github.io/issues/2", "commentNum": 0, "wordCount": 583, "description": "### \u6700\u8fd1\u6ca1\u6709\u4ec0\u4e48\u5927\u4e8b\u53d1\u751f\uff0c\u4f46\u4ecd\u611f\u5230\u5fc3\u529b\u6194\u60b4\n**\u671f\u4e2d\u8003\u8bd5\u7684\u4f59\u70ed\u8fd8\u672a\u892a\u53bb\uff0c\u63a5\u4e0b\u6765\u4e0a\u573a\u7684\u662f\u57f9\u4f18\u8054\u76df\u8003**\n\n- \u4e0a\u6b21\u7684\u6210\u7ee9\u4e0d\u5c3d\u4eba\u610f\uff0c\u8fd9\u6b21\u6211\u611f\u89c9\u8fd8\u662f\u8981\u5bc4\n\n\u5f53\u6211\u5750\u5728\u8003\u573a\u65f6\uff0c\u90a3\u65f6\u7684\u6211\u4f1a\u60f3\u4e9b\u4ec0\u4e48\uff1f\n\u662f\u5728\u540e\u6094\u524d\u4e9b\u5929\u5b66\u4e60\u7684\u6d51\u6d51\u5669\u5669\uff0c\u8fd8\u662f\u60f3\u7740\u5bb6\u91cc\u7684\u5c0f\u4e1b\u96e8\u5728\u7b49\u7740\u6211\u5462\uff1f\u6211\u60f3\u5e94\u8be5\u662f\u540e\u8005\u5427\u3002", "top": 0, "createdAt": 1764436867, "style": "", "script": "<script src='https://blog.meekdai.com/Gmeek/plugins/GmeekTOC.js'></script><script src='https://blog.meekdai.com/Gmeek/plugins/lightbox.js'></script>", "head": "", "ogImage": "https://avatars.githubusercontent.com/u/237422127?v=4", "createdDate": "2025-11-30", "dateLabelColor": "#0969da"}}, "singeListJson": {}, "labelColorDict": {"bug": "#d73a4a", "documentation": "#0075ca", "duplicate": "#cfd3d7", "enhancement": "#a2eeef", "good first issue": "#7057ff", "help wanted": "#008672", "invalid": "#e4e669", "question": "#d876e3", "wontfix": "#ffffff", "\u52a8\u753b": "#e739f9", "\u53d1\u7535": "#9fe936", "\u65e5\u5e38": "#18abdb", "\u788e\u788e\u5ff5": "#2f2625", "\u8bb0\u5f55": "#f69134"}, "displayTitle": "\u30e6\u30ad\u306e\u90e8\u5c4b", "faviconUrl": "https://avatars.githubusercontent.com/u/237422127?v=4", "ogImage": "https://avatars.githubusercontent.com/u/237422127?v=4", "primerCSS": "<link href='https://mirrors.sustech.edu.cn/cdnjs/ajax/libs/Primer/21.0.7/primer.css' rel='stylesheet' />", "homeUrl": "https://zfyx-ice.github.io", "prevUrl": "disabled", "nextUrl": "disabled"}